firedom/__init__.py
firedom/collection.py
firedom/field.py
firedom/firedom.py
firedom/model.py
firedom/utils.py
firedom-1.3.0.dist-info/LICENSE
firedom-1.3.0.dist-info/METADATA
firedom-1.3.0.dist-info/WHEEL
firedom-1.3.0.dist-info/top_level.txt
firedom-1.3.0.dist-info/RECORD
