Metadata-Version: 2.1
Name: firedom
Version: 1.3.0
Summary: Simple Firestore ORM
Home-page: https://github.com/afuenzalida/firedom
Author: Andrés Fuenzalida
Author-email: a.fuenzalida1494@gmail.com
License: MIT
Classifier: License :: OSI Approved :: MIT License
Classifier: Programming Language :: Python :: 3.11
License-File: LICENSE
Requires-Dist: google-cloud-firestore >=2.13.1
